config.yml
schematic/__init__.py
schematic/__main__.py
schematic/configuration.py
schematic/etc/README.md
schematic/etc/data_models/biothings.model.jsonld
schematic/etc/data_models/schema_org.model.jsonld
schematic/etc/validation_schemas/class.schema.json
schematic/etc/validation_schemas/model.schema.json
schematic/etc/validation_schemas/property.schema.json
schematic/exceptions.py
schematic/loader.py
schematic/manifest/README.md
schematic/manifest/__init__.py
schematic/manifest/commands.py
schematic/manifest/examples/generator_usage.py
schematic/manifest/generator.py
schematic/models/README.md
schematic/models/__init__.py
schematic/models/commands.py
schematic/models/examples/metadata_usage.py
schematic/models/metadata.py
schematic/schemas/README.md
schematic/schemas/__init__.py
schematic/schemas/curie.py
schematic/schemas/examples/explorer_usage.py
schematic/schemas/examples/generator_usage.py
schematic/schemas/explorer.py
schematic/schemas/generator.py
schematic/schemas/validator.py
schematic/store/README.md
schematic/store/__init__.py
schematic/store/base.py
schematic/store/examples/store_usage.py
schematic/store/synapse.py
schematic/utils/__init__.py
schematic/utils/cli_utils.py
schematic/utils/csv_utils.py
schematic/utils/curie_utils.py
schematic/utils/df_utils.py
schematic/utils/examples/csv_to_schemaorg_usage.py
schematic/utils/general.py
schematic/utils/google_api_utils.py
schematic/utils/io_utils.py
schematic/utils/schema_utils.py
schematic/utils/validate_utils.py
schematic/utils/viz_utils.py
schematic/version.py
schematic_test-0.1.11.dist-info/entry_points.txt
schematic_test-0.1.11.dist-info/WHEEL
schematic_test-0.1.11.dist-info/METADATA
schematic_test-0.1.11.dist-info/RECORD
