Metadata-Version: 2.1
Name: schematic-test
Version: 0.1.11
Summary: Package for data model and data ingress management
Home-page: https://github.com/Sage-Bionetworks/schematic
License: MIT
Keywords: schema,metadata,validation,schema.org,data model
Author: Milen Nikolov
Author-email: milen.nikolov@sagebase.org
Requires-Python: >=3.7.1,<4.0.0
Classifier: Development Status :: 4 - Beta
Classifier: Environment :: Console
Classifier: Intended Audience :: Science/Research
Classifier: License :: OSI Approved :: MIT License
Classifier: Programming Language :: Python :: 3
Classifier: Programming Language :: Python :: 3.8
Classifier: Programming Language :: Python :: 3.9
Classifier: Topic :: Software Development :: Libraries :: Python Modules
Requires-Dist: PyYAML (>=5.4.1,<6.0.0)
Requires-Dist: click (>=7.1.2,<8.0.0)
Requires-Dist: click-log (>=0.3.2,<0.4.0)
Requires-Dist: fastjsonschema (>=2.14.5,<3.0.0)
Requires-Dist: google-api-python-client (>=1.12.8,<2.0.0)
Requires-Dist: google-auth-httplib2 (>=0.0.4,<0.0.5)
Requires-Dist: google-auth-oauthlib (>=0.4.2,<0.5.0)
Requires-Dist: graphviz (>=0.16,<0.17)
Requires-Dist: importlib-metadata (>=1.6.0,<2.0.0); python_version < "3.8"
Requires-Dist: inflection (>=0.5.1,<0.6.0)
Requires-Dist: jsonschema (>=3.2.0,<4.0.0)
Requires-Dist: networkx (>=2.5,<3.0)
Requires-Dist: orderedset (>=2.0.3,<3.0.0)
Requires-Dist: pandas (>=1.2.1,<2.0.0)
Requires-Dist: pygsheets (>=2.0.4,<3.0.0)
Requires-Dist: rdflib (>=5.0.0,<6.0.0)
Requires-Dist: synapseclient (>=2.2.2,<3.0.0)
Requires-Dist: tabletext (>=0.1,<0.2)
Project-URL: Documentation, https://github.com/Sage-Bionetworks/schematic
Project-URL: Repository, https://github.com/Sage-Bionetworks/schematic
